setup.py
oupengauth/__init__.py
oupengauth/oauth.py
oupengauth/qq.py
oupengauth/renren.py
oupengauth/sina.py
oupengauth/taobao.py
oupengauth.egg-info/PKG-INFO
oupengauth.egg-info/SOURCES.txt
oupengauth.egg-info/dependency_links.txt
oupengauth.egg-info/top_level.txt