Metadata-Version: 1.0
Name: oupengauth
Version: 0.1.2
Summary: A oauth client library.
Home-page: http://oupeng.com
Author: kula
Author-email: kulasama@gmail.com
License: UNKNOWN
Platform: UNKNOWN
